CHANGES.txt
LICENSE.txt
MANIFEST.in
README.rst
setup.py
plonesocial/__init__.py
plonesocial.theme.egg-info/PKG-INFO
plonesocial.theme.egg-info/SOURCES.txt
plonesocial.theme.egg-info/dependency_links.txt
plonesocial.theme.egg-info/entry_points.txt
plonesocial.theme.egg-info/namespace_packages.txt
plonesocial.theme.egg-info/not-zip-safe
plonesocial.theme.egg-info/requires.txt
plonesocial.theme.egg-info/top_level.txt
plonesocial/theme/__init__.py
plonesocial/theme/configure.zcml
plonesocial/theme/profiles/default/cssregistry.xml
plonesocial/theme/profiles/default/metadata.xml
plonesocial/theme/profiles/default/theme.xml
plonesocial/theme/static/404.html
plonesocial/theme/static/apple-touch-icon-114x114-precomposed.png
plonesocial/theme/static/apple-touch-icon-57x57-precomposed.png
plonesocial/theme/static/apple-touch-icon-72x72-precomposed.png
plonesocial/theme/static/apple-touch-icon-precomposed.png
plonesocial/theme/static/apple-touch-icon.png
plonesocial/theme/static/base.html
plonesocial/theme/static/crossdomain.xml
plonesocial/theme/static/dialog.html
plonesocial/theme/static/facetednavigation-rules.xml
plonesocial/theme/static/favicon.ico
plonesocial/theme/static/htmltidy.pl
plonesocial/theme/static/humans.txt
plonesocial/theme/static/jquery-1.7.1.min.js
plonesocial/theme/static/manifest.cfg
plonesocial/theme/static/navigation-rules.xml
plonesocial/theme/static/portlet-rules.xml
plonesocial/theme/static/robots.txt
plonesocial/theme/static/rules.xml
plonesocial/theme/static/bootstrap/css/bootstrap-responsive.css
plonesocial/theme/static/bootstrap/css/bootstrap-responsive.min.css
plonesocial/theme/static/bootstrap/css/bootstrap.css
plonesocial/theme/static/bootstrap/css/bootstrap.min.css
plonesocial/theme/static/bootstrap/img/glyphicons-halflings-white.png
plonesocial/theme/static/bootstrap/img/glyphicons-halflings.png
plonesocial/theme/static/bootstrap/js/bootstrap.js
plonesocial/theme/static/bootstrap/js/bootstrap.min.js
plonesocial/theme/static/css/editview.css
plonesocial/theme/static/css/public.css
plonesocial/theme/static/css/reset.css
plonesocial/theme/static/css/theme.css
plonesocial/theme/static/html5slides/prettify.js
plonesocial/theme/static/html5slides/slides.js
plonesocial/theme/static/html5slides/styles.css
plonesocial/theme/static/html5slides/images/colorbar.png
