Metadata-Version: 1.1
Name: plonesocial.theme
Version: 0.5.2
Summary: Plone theme based on Twitter's Bootstrap CSS
Home-page: https://github.com/cosent/plonesocial.theme
Author: Guido Stevens / Based on work by Izhar Firdaus
Author-email: guido.stevens@cosent.net
License: Apache License 2.0
Keywords: plone diazo theme
Platform: UNKNOWN
Classifier: Programming Language :: Python
